bccr/__init__.py
bccr/download.py
bccr/fetch.py
bccr/gee.py
bccr/gui.py
bccr/pagina.py
bccr/scrape.py
bccr/utils.py
bccr/data/cuadros.pkl
bccr/data/indicadores.pkl
bccr/data/indicators.pkl
bccr-2022.6.29.dist-info/LICENSE.txt
bccr-2022.6.29.dist-info/METADATA
bccr-2022.6.29.dist-info/WHEEL
bccr-2022.6.29.dist-info/top_level.txt
bccr-2022.6.29.dist-info/RECORD
