Metadata-Version: 2.1
Name: bccr
Version: 2022.6.29
Summary: Herramientas para descargar datos del Banco Central de Costa Rica
Home-page: http://randall-romero.com/code/bccr
Author: Randall Romero-Aguilar
Author-email: randall.romero@outlook.com
License: MIT
Keywords: BCCR datos
Platform: UNKNOWN
Requires-Python: >=3.7
License-File: LICENSE.txt
Requires-Dist: pandas
Requires-Dist: numpy
Requires-Dist: anytree
Requires-Dist: requests
Requires-Dist: beautifulsoup4
Requires-Dist: plotly
Requires-Dist: dash (>=2.2.0)
Requires-Dist: dash-extensions (==0.0.71)
Requires-Dist: jupyter-dash
